<?xml version="1.0" encoding="utf-8" ?><dwsync><file name="banner-beckwith.jpg" server="ftp.subtextinc.com//httpdocs/npe/" local="3436843998" remote="12032186672" /><file name="banner-jtx.jpg" server="ftp.subtextinc.com//httpdocs/npe/" local="3436844376" remote="12032186732" /><file name="Main-Banner-Melodrama.jpg" server="ftp.subtextinc.com//httpdocs/npe/" local="3441410594" remote="12032186732" /><file name="Main-Banner-Melodrama.jpg" server="s162242.gridserver.com/domains/nextplateauent.com/html/" local="3442197600" remote="20622066784" /><file name="banner-beckwith.jpg" server="s162242.gridserver.com/domains/nextplateauent.com/html/" local="3442197600" remote="20622066784" /><file name="banner-jtx.jpg" server="s162242.gridserver.com/domains/nextplateauent.com/html/" local="3444357600" remote="20624226784" /><file name="banner-beckwith.jpg" server="s162242.gridserver.com/domains/nextplateauent.com/html/test/" local="3442249920" remote="12042678212" /><file name="banner-jtx.jpg" server="s162242.gridserver.com/domains/nextplateauent.com/html/test/" local="3444389940" remote="12042678212" /><file name="Main-Banner-Melodrama.jpg" server="s162242.gridserver.com/domains/nextplateauent.com/html/test/" local="3442249920" remote="12042678272" /><file name="BEATPORTBANNER-PRERELEASE.JPG" server="s162242.gridserver.com/domains/nextplateauent.com/html/" local="3448846800" remote="20628715984" /><file name="HURRICANEBANNER-PRERELEASE.jpg" server="s162242.gridserver.com/domains/nextplateauent.com/html/" local="3448846800" remote="20628715984" /><file name="JTXSevenDayBanner.JPG" server="s162242.gridserver.com/domains/nextplateauent.com/html/" local="3453858000" remote="20633727184" /><file name="Jax&CoreySadTruthBanner.JPG" server="s162242.gridserver.com/domains/nextplateauent.com/html/" local="3448846800" remote="20628715984" /><file name="MilanandPhoenixArtworkresized.jpg" server="s162242.gridserver.com/domains/nextplateauent.com/html/" local="3444357600" remote="20624226784" /><file name="MilanandPhoenixArtworkresized2.jpg" server="s162242.gridserver.com/domains/nextplateauent.com/html/" local="3444357600" remote="20624226784" /><file name="Screenshot2013-02-22at11.00.09AM.png" server="s162242.gridserver.com/domains/nextplateauent.com/html/" local="3444357600" remote="20624226784" /><file name="Screenshot2013-02-22at11.05.06AM.jpg" server="s162242.gridserver.com/domains/nextplateauent.com/html/" local="3444357600" remote="20624226784" /><file name="Screenshot2013-02-22at11.05.06AM2.jpg" server="s162242.gridserver.com/domains/nextplateauent.com/html/" local="3444616800" remote="20624485984" /><file name="TheSadTruthbanner2p.jpg" server="s162242.gridserver.com/domains/nextplateauent.com/html/" local="3444357600" remote="20624226784" /><file name="TheSadTruthbanner2yellow.jpg" server="s162242.gridserver.com/domains/nextplateauent.com/html/" local="3444357600" remote="20624226784" /><file name="TheSadTruthbannercoloritalicsresize.jpg" server="s162242.gridserver.com/domains/nextplateauent.com/html/" local="3444357600" remote="20624226784" /><file name="WhatDoesTomorrowBringbanner.jpg" server="s162242.gridserver.com/domains/nextplateauent.com/html/" local="3444703200" remote="20624572384" /><file name="WhatDoesTomorrowBringbanner2.jpg" server="s162242.gridserver.com/domains/nextplateauent.com/html/" local="3444703200" remote="20624572384" /><file name="banner-7daywknd.jpg" server="s162242.gridserver.com/domains/nextplateauent.com/html/" local="3444876000" remote="20624745184" /><file name="banner-concreteangel.jpg" server="s162242.gridserver.com/domains/nextplateauent.com/html/" local="3444876000" remote="20624745184" /><file name="banner-instanbul.jpg" server="s162242.gridserver.com/domains/nextplateauent.com/html/" local="3444876000" remote="20624745184" /><file name="banner-sadtruth.jpg" server="s162242.gridserver.com/domains/nextplateauent.com/html/" local="3444876000" remote="20624745184" /><file name="banner-whatdoestmrwbring.jpg" server="s162242.gridserver.com/domains/nextplateauent.com/html/" local="3444876000" remote="20624745184" /><file name="concreteangelbanner.jpg" server="s162242.gridserver.com/domains/nextplateauent.com/html/" local="3444357600" remote="20624226784" /><file name="concreteangelbannerj.jpg" server="s162242.gridserver.com/domains/nextplateauent.com/html/" local="3444789600" remote="20624658784" /><file name="banner-7daywknd.jpg" server="s162242.gridserver.com/domains/nextplateauent.com/html/test/" local="3444949740" remote="12042678212" /><file name="banner-concreteangel.jpg" server="s162242.gridserver.com/domains/nextplateauent.com/html/test/" local="3444949800" remote="12042678212" /><file name="banner-instanbul.jpg" server="s162242.gridserver.com/domains/nextplateauent.com/html/test/" local="3444949680" remote="12042678212" /><file name="banner-sadtruth.jpg" server="s162242.gridserver.com/domains/nextplateauent.com/html/test/" local="3444949740" remote="12042678212" /><file name="banner-whatdoestmrwbring.jpg" server="s162242.gridserver.com/domains/nextplateauent.com/html/test/" local="3444949800" remote="12042678212" /><file name="BEATPORTBANNER-PRERELEASE.JPG" server="s162242.gridserver.com/domains/nextplateauent.com/html/test/" local="3448874820" remote="12042678272" /><file name="concreteangelbanner.jpg" server="s162242.gridserver.com/domains/nextplateauent.com/html/test/" local="3444413220" remote="12042678272" /><file name="concreteangelbannerj.jpg" server="s162242.gridserver.com/domains/nextplateauent.com/html/test/" local="3444821940" remote="12042678272" /><file name="HURRICANEBANNER-PRERELEASE.jpg" server="s162242.gridserver.com/domains/nextplateauent.com/html/test/" local="3448898280" remote="12042678272" /><file name="Jax&CoreySadTruthBanner.JPG" server="s162242.gridserver.com/domains/nextplateauent.com/html/test/" local="3448876080" remote="12042678272" /><file name="JTXSevenDayBanner.JPG" server="s162242.gridserver.com/domains/nextplateauent.com/html/test/" local="3450184140" remote="12042678272" /><file name="MilanandPhoenixArtworkresized.jpg" server="s162242.gridserver.com/domains/nextplateauent.com/html/test/" local="3444397020" remote="12042678272" /><file name="MilanandPhoenixArtworkresized2.jpg" server="s162242.gridserver.com/domains/nextplateauent.com/html/test/" local="3444399840" remote="12042678272" /><file name="Screenshot2013-02-22at11.00.09AM.png" server="s162242.gridserver.com/domains/nextplateauent.com/html/test/" local="3444390060" remote="12042678272" /><file name="Screenshot2013-02-22at11.05.06AM.jpg" server="s162242.gridserver.com/domains/nextplateauent.com/html/test/" local="3444390360" remote="12042678272" /><file name="Screenshot2013-02-22at11.05.06AM2.jpg" server="s162242.gridserver.com/domains/nextplateauent.com/html/test/" local="3444673920" remote="12042678272" /><file name="TheSadTruthbanner2p.jpg" server="s162242.gridserver.com/domains/nextplateauent.com/html/test/" local="3444410580" remote="12042678272" /><file name="TheSadTruthbanner2yellow.jpg" server="s162242.gridserver.com/domains/nextplateauent.com/html/test/" local="3444413700" remote="12042678272" /><file name="TheSadTruthbannercoloritalicsresize.jpg" server="s162242.gridserver.com/domains/nextplateauent.com/html/test/" local="3444403020" remote="12042678272" /><file name="WhatDoesTomorrowBringbanner.jpg" server="s162242.gridserver.com/domains/nextplateauent.com/html/test/" local="3444748260" remote="12042678272" /><file name="WhatDoesTomorrowBringbanner2.jpg" server="s162242.gridserver.com/domains/nextplateauent.com/html/test/" local="3444760620" remote="12042678272" /><file name="SummerLoverArtwork.jpg" server="s162242.gridserver.com/domains/nextplateauent.com/html/" local="3453858000" remote="20633727184" /><file name="Wildstylez-LightsGoOut.jpg" server="s162242.gridserver.com/domains/nextplateauent.com/html/" local="3463738020" remote="20643607204" /><file name="banner-7daywknd.jpg" server="ftp.subtextinc.com/NPE/" local="3444876000" remote="12059484392" /><file name="banner-beckwith.jpg" server="ftp.subtextinc.com/NPE/" local="3442197600" remote="12059484392" /><file name="banner-concreteangel.jpg" server="ftp.subtextinc.com/NPE/" local="3444876000" remote="12059484392" /><file name="banner-instanbul.jpg" server="ftp.subtextinc.com/NPE/" local="3444876000" remote="12059484392" /><file name="banner-jtx.jpg" server="ftp.subtextinc.com/NPE/" local="3444357600" remote="12059484392" /><file name="banner-sadtruth.jpg" server="ftp.subtextinc.com/NPE/" local="3444876000" remote="12059484392" /><file name="banner-whatdoestmrwbring.jpg" server="ftp.subtextinc.com/NPE/" local="3444876000" remote="12059484392" /><file name="BEATPORTBANNER-PRERELEASE.JPG" server="ftp.subtextinc.com/NPE/" local="3448846800" remote="12059484392" /><file name="concreteangelbanner.jpg" server="ftp.subtextinc.com/NPE/" local="3444357600" remote="12059484392" /><file name="concreteangelbannerj.jpg" server="ftp.subtextinc.com/NPE/" local="3444789600" remote="12059484392" /><file name="HURRICANEBANNER-PRERELEASE.jpg" server="ftp.subtextinc.com/NPE/" local="3448846800" remote="12059484392" /><file name="Jax&CoreySadTruthBanner.JPG" server="ftp.subtextinc.com/NPE/" local="3448846800" remote="12059484392" /><file name="JTXSevenDayBanner.JPG" server="ftp.subtextinc.com/NPE/" local="3453858000" remote="12059484392" /><file name="Main-Banner-Melodrama.jpg" server="ftp.subtextinc.com/NPE/" local="3442197600" remote="12059484392" /><file name="MilanandPhoenixArtworkresized.jpg" server="ftp.subtextinc.com/NPE/" local="3444357600" remote="12059484392" /><file name="MilanandPhoenixArtworkresized2.jpg" server="ftp.subtextinc.com/NPE/" local="3444357600" remote="12059484392" /><file name="Screenshot2013-02-22at11.00.09AM.png" server="ftp.subtextinc.com/NPE/" local="3444357600" remote="12059484392" /><file name="Screenshot2013-02-22at11.05.06AM.jpg" server="ftp.subtextinc.com/NPE/" local="3444357600" remote="12059484392" /><file name="Screenshot2013-02-22at11.05.06AM2.jpg" server="ftp.subtextinc.com/NPE/" local="3444616800" remote="12059484452" /><file name="TheSadTruthbanner2p.jpg" server="ftp.subtextinc.com/NPE/" local="3444357600" remote="12059484452" /><file name="TheSadTruthbanner2yellow.jpg" server="ftp.subtextinc.com/NPE/" local="3444357600" remote="12059484452" /><file name="TheSadTruthbannercoloritalicsresize.jpg" server="ftp.subtextinc.com/NPE/" local="3444357600" remote="12059484452" /><file name="WhatDoesTomorrowBringbanner.jpg" server="ftp.subtextinc.com/NPE/" local="3444703200" remote="12059484452" /><file name="WhatDoesTomorrowBringbanner2.jpg" server="ftp.subtextinc.com/NPE/" local="3444703200" remote="12059484452" /><file name="SummerLoverArtwork.jpg" server="ftp.subtextinc.com/NPE/" local="3453858000" remote="12059484452" /><file name="Wildstylez-LightsGoOut.jpg" server="ftp.subtextinc.com/NPE/" local="3463738020" remote="12059484452" /></dwsync>