<?xml version="1.0" encoding="utf-8" ?><dwsync><file name="NP2814.jpg" server="s162242.gridserver.com/domains/nextplateauent.com/html/" local="3442975200" remote="20622844384" /><file name="NP2816.jpg" server="s162242.gridserver.com/domains/nextplateauent.com/html/" local="3442975200" remote="20622844384" /><file name="NP2820.jpg" server="s162242.gridserver.com/domains/nextplateauent.com/html/" local="3442975200" remote="20622844384" /><file name="rca.jpg" server="s162242.gridserver.com/domains/nextplateauent.com/html/" local="3442975200" remote="20622844384" /><file name="tce2.jpg" server="s162242.gridserver.com/domains/nextplateauent.com/html/" local="3442975200" remote="20622844384" /><file name="default.jpg" server="s162242.gridserver.com/domains/nextplateauent.com/html/test/" local="3445670413" remote="12042678392" /><file name="NP2814.jpg" server="s162242.gridserver.com/domains/nextplateauent.com/html/test/" local="3442990980" remote="12042678512" /><file name="NP2816.jpg" server="s162242.gridserver.com/domains/nextplateauent.com/html/test/" local="3442990980" remote="12042678512" /><file name="NP2820.jpg" server="s162242.gridserver.com/domains/nextplateauent.com/html/test/" local="3442990980" remote="12042678512" /><file name="rca.jpg" server="s162242.gridserver.com/domains/nextplateauent.com/html/test/" local="3442990980" remote="12042678512" /><file name="tce2.jpg" server="s162242.gridserver.com/domains/nextplateauent.com/html/test/" local="3442990980" remote="12042678512" /><file name="11.jpg" server="s162242.gridserver.com/domains/nextplateauent.com/html/" local="3444012000" remote="20623881184" /><file name="13.jpg" server="s162242.gridserver.com/domains/nextplateauent.com/html/" local="3444012000" remote="20623881184" /><file name="310152_10150292510055256_5154834_n.jpg" server="s162242.gridserver.com/domains/nextplateauent.com/html/" local="3443148000" remote="20623017184" /><file name="33.jpg" server="s162242.gridserver.com/domains/nextplateauent.com/html/" local="3444012000" remote="20623881184" /><file name="ADESampler2012lowres.jpg" server="s162242.gridserver.com/domains/nextplateauent.com/html/" local="3444357600" remote="20624226784" /><file name="AlexSayz-HateToLovecoverlowres.jpg" server="s162242.gridserver.com/domains/nextplateauent.com/html/" local="3443752800" remote="20623621984" /><file name="AlexSayz-ShameOnMeCoverlowres.jpg" server="s162242.gridserver.com/domains/nextplateauent.com/html/" local="3443752800" remote="20623621984" /><file name="AlexSayz_UnitedAsOnelowres.jpg" server="s162242.gridserver.com/domains/nextplateauent.com/html/" local="3443752800" remote="20623621984" /><file name="AntoineClamaran-Gold.jpg" server="s162242.gridserver.com/domains/nextplateauent.com/html/" local="3444271200" remote="20624140384" /><file name="AntoineClamaranLiveYourDreams.jpg" server="s162242.gridserver.com/domains/nextplateauent.com/html/" local="3444271200" remote="20624140384" /><file name="AntoineClamaranReachfortheStars.JPG" server="s162242.gridserver.com/domains/nextplateauent.com/html/" local="3444271200" remote="20624140384" /><file name="AntoineEclypseArt.JPG" server="s162242.gridserver.com/domains/nextplateauent.com/html/" local="3444271200" remote="20624140384" /><file name="Bailey_HigherState.jpg" server="s162242.gridserver.com/domains/nextplateauent.com/html/" local="3443752800" remote="20623621984" /><file name="Baileyfeat.JodieConor-HigherState.jpg" server="s162242.gridserver.com/domains/nextplateauent.com/html/" local="3449192400" remote="20629061584" /><file name="Beckwith-HigherYourLove.JPG" server="s162242.gridserver.com/domains/nextplateauent.com/html/" local="3443752800" remote="20623621984" /><file name="Beckwith-NOTIMETOWASTEFinalCover.jpg" server="s162242.gridserver.com/domains/nextplateauent.com/html/" local="3443752800" remote="20623621984" /><file name="BeckwithfeatIneabell-Higher(YourLove).jpg" server="s162242.gridserver.com/domains/nextplateauent.com/html/" local="3449192400" remote="20629061584" /><file name="BowCoverArtwork.jpg" server="s162242.gridserver.com/domains/nextplateauent.com/html/" local="3444271200" remote="20624140384" /><file name="ButterfliesCoverArtwork.jpg" server="s162242.gridserver.com/domains/nextplateauent.com/html/" local="3444271200" remote="20624140384" /><file name="ChanelleHayes-IWantIt.jpg" server="s162242.gridserver.com/domains/nextplateauent.com/html/" local="3449192400" remote="20629061584" /><file name="ChilloutExperience-BeatlesTributelowres.jpg" server="s162242.gridserver.com/domains/nextplateauent.com/html/" local="3444357600" remote="20624226784" /><file name="ConcreteAngelOFFICIALRemixesArtwork.jpg" server="s162242.gridserver.com/domains/nextplateauent.com/html/" local="3443752800" remote="20623621984" /><file name="CoverArtDigital-FINALlowres.jpg" server="s162242.gridserver.com/domains/nextplateauent.com/html/" local="3443752800" remote="20623621984" /><file name="CraigSmart-123.jpg" server="s162242.gridserver.com/domains/nextplateauent.com/html/" local="3449192400" remote="20629061584" /><file name="CraigSmart123CoverArt.jpg" server="s162242.gridserver.com/domains/nextplateauent.com/html/" local="3443752800" remote="20623621984" /><file name="DJElla-ShineLikeaSuperstar.jpg" server="s162242.gridserver.com/domains/nextplateauent.com/html/" local="3449192400" remote="20629061584" /><file name="DJElla-WelcometotheClub.jpg" server="s162242.gridserver.com/domains/nextplateauent.com/html/" local="3449192400" remote="20629061584" /><file name="DJElla_ShineLikeASuperstar_Cover.jpg" server="s162242.gridserver.com/domains/nextplateauent.com/html/" local="3443752800" remote="20623621984" /><file name="DJZipDJELLA.jpg" server="s162242.gridserver.com/domains/nextplateauent.com/html/" local="3443752800" remote="20623621984" /><file name="DamienS-LongLostSummerLove.jpg" server="s162242.gridserver.com/domains/nextplateauent.com/html/" local="3449192400" remote="20629061584" /><file name="DamienS-LongLostSummerLoveArtwork.jpg" server="s162242.gridserver.com/domains/nextplateauent.com/html/" local="3443752800" remote="20623621984" /><file name="DavidPuentez-Envy.jpg" server="s162242.gridserver.com/domains/nextplateauent.com/html/" local="3449192400" remote="20629061584" /><file name="DavidPuentez-EnvyCoverArt.jpg" server="s162242.gridserver.com/domains/nextplateauent.com/html/" local="3443752800" remote="20623621984" /><file name="DavidPuentez-Melodrama.jpg" server="s162242.gridserver.com/domains/nextplateauent.com/html/" local="3449192400" remote="20629061584" /><file name="DavidPuentez_Melodrama_Coverart.jpg" server="s162242.gridserver.com/domains/nextplateauent.com/html/" local="3443752800" remote="20623621984" /><file name="DavidPuentezfeat.AndreaRosario-Melodrama(LoseControlVocal).jpg" server="s162242.gridserver.com/domains/nextplateauent.com/html/" local="3449192400" remote="20629061584" /><file name="DavidPuentezfeat.AndreaRosario-Melodrama-LoseControl-Coverart.jpg" server="s162242.gridserver.com/domains/nextplateauent.com/html/" local="3443752800" remote="20623621984" /><file name="Ela-Rose-I-Can-Feel.jpg" server="s162242.gridserver.com/domains/nextplateauent.com/html/" local="3443752800" remote="20623621984" /><file name="ElaWardi-IfYouCouldReadMyMind.jpg" server="s162242.gridserver.com/domains/nextplateauent.com/html/" local="3449192400" remote="20629061584" /><file name="Ela_Wardi_Stars_on_54Artwork.jpg" server="s162242.gridserver.com/domains/nextplateauent.com/html/" local="3443752800" remote="20623621984" /><file name="Freedom_cover.jpg" server="s162242.gridserver.com/domains/nextplateauent.com/html/" local="3443752800" remote="20623621984" /><file name="GETFAR-FREE.jpg" server="s162242.gridserver.com/domains/nextplateauent.com/html/" local="3443752800" remote="20623621984" /><file name="GarethEmeryfeatChristinaNovelli%22ConcreteAngel%22.jpg" server="s162242.gridserver.com/domains/nextplateauent.com/html/" local="3443752800" remote="20623621984" /><file name="GarethEmeryfeatChristinaNovelli%22ConcreteAngel%22lowres.jpg" server="s162242.gridserver.com/domains/nextplateauent.com/html/" local="3443752800" remote="20623621984" /><file name="GarethEmeryfeatChristinaNovelliConcreteAngellowres.jpg" server="s162242.gridserver.com/domains/nextplateauent.com/html/" local="3443752800" remote="20623621984" /><file name="GetFar-TheRadio.jpg" server="s162242.gridserver.com/domains/nextplateauent.com/html/" local="3449192400" remote="20629061584" /><file name="GetFar_TheRadio.jpg" server="s162242.gridserver.com/domains/nextplateauent.com/html/" local="3443752800" remote="20623621984" /><file name="GottaLoveForYouCover.jpg" server="s162242.gridserver.com/domains/nextplateauent.com/html/" local="3444271200" remote="20624140384" /><file name="HeadShouldersKneezToez.jpg" server="s162242.gridserver.com/domains/nextplateauent.com/html/" local="3444271200" remote="20624140384" /><file name="HeartbrokenArtworkCover.jpg" server="s162242.gridserver.com/domains/nextplateauent.com/html/" local="3444271200" remote="20624140384" /><file name="HurricaneArtforRelease.jpg" server="s162242.gridserver.com/domains/nextplateauent.com/html/" local="3451266000" remote="20631135184" /><file name="IanCareyftSnoopDogg&BobbyAnthony-LastNight(FullCover).jpg" server="s162242.gridserver.com/domains/nextplateauent.com/html/" local="3443752800" remote="20623621984" /><file name="IanCareyftSnoopDogg&BobbyAnthony-LastNight(FullCover)lowres.jpg" server="s162242.gridserver.com/domains/nextplateauent.com/html/" local="3443752800" remote="20623621984" /><file name="IanCareyftSnoopDoggBobbyAnthony-LastNightlowres.jpg" server="s162242.gridserver.com/domains/nextplateauent.com/html/" local="3443752800" remote="20623621984" /><file name="J-Status-AllRise.jpg" server="s162242.gridserver.com/domains/nextplateauent.com/html/" local="3444271200" remote="20624140384" /><file name="J-Status-Pieces.jpg" server="s162242.gridserver.com/domains/nextplateauent.com/html/" local="3444271200" remote="20624140384" /><file name="JTX-7DayWeekend-iTuneslowres.jpg" server="s162242.gridserver.com/domains/nextplateauent.com/html/" local="3443752800" remote="20623621984" /><file name="JTX-LoveInAmerica.jpg" server="s162242.gridserver.com/domains/nextplateauent.com/html/" local="3443752800" remote="20623621984" /><file name="JTX-PartyLikeaRockstar.jpg" server="s162242.gridserver.com/domains/nextplateauent.com/html/" local="3449192400" remote="20629061584" /><file name="JTXFromDetroitArtwork.jpg" server="s162242.gridserver.com/domains/nextplateauent.com/html/" local="3444357600" remote="20624226784" /><file name="JTXLoveinAmericaRemixes.jpg" server="s162242.gridserver.com/domains/nextplateauent.com/html/" local="3444357600" remote="20624226784" /><file name="Jameerahalleyesonme.jpg" server="s162242.gridserver.com/domains/nextplateauent.com/html/" local="3444789600" remote="20624658784" /><file name="JaxBerlin&CoreyPhillips-TheSadTruth.jpg" server="s162242.gridserver.com/domains/nextplateauent.com/html/" local="3449192400" remote="20629061584" /><file name="Jersey-Italycopy.jpeg" server="s162242.gridserver.com/domains/nextplateauent.com/html/" local="3444357600" remote="20624226784" /><file name="Jersey-Miami-Vol2copy.jpg" server="s162242.gridserver.com/domains/nextplateauent.com/html/" local="3444357600" remote="20624226784" /><file name="JerseyMiami_600x600.jpg" server="s162242.gridserver.com/domains/nextplateauent.com/html/" local="3444357600" remote="20624226784" /><file name="KateRyanCover.jpg" server="s162242.gridserver.com/domains/nextplateauent.com/html/" local="3444271200" remote="20624140384" /><file name="Katerine-AyoTechnology(Remixes).jpg" server="s162242.gridserver.com/domains/nextplateauent.com/html/" local="3444271200" remote="20624140384" /><file name="LiquidNation-BreatheLifeCoverArt.jpg" server="s162242.gridserver.com/domains/nextplateauent.com/html/" local="3444271200" remote="20624140384" /><file name="Longo&Wainwright-OneLifeStand.jpg" server="s162242.gridserver.com/domains/nextplateauent.com/html/" local="3449192400" remote="20629061584" /><file name="Loveshy-TheBoyisMineCover.jpg" server="s162242.gridserver.com/domains/nextplateauent.com/html/" local="3444271200" remote="20624140384" /><file name="Maniacalm-IMissYou.jpg" server="s162242.gridserver.com/domains/nextplateauent.com/html/" local="3444271200" remote="20624140384" /><file name="MilanandPhoenixArtwork.jpg" server="s162242.gridserver.com/domains/nextplateauent.com/html/" local="3444357600" remote="20624226784" /><file name="MorrisCortiIRockISweatIDanceArtwork.jpg" server="s162242.gridserver.com/domains/nextplateauent.com/html/" local="3444962400" remote="20624831584" /><file name="NPEJoubertSingersTheRemixes2012.jpg" server="s162242.gridserver.com/domains/nextplateauent.com/html/" local="3444271200" remote="20624140384" /><file name="NPE_Joubert_Singers.jpg" server="s162242.gridserver.com/domains/nextplateauent.com/html/" local="3444271200" remote="20624140384" /><file name="NobodyFallsNewArtworklowres.jpg" server="s162242.gridserver.com/domains/nextplateauent.com/html/" local="3443752800" remote="20623621984" /><file name="OneLifeStandcover.jpg" server="s162242.gridserver.com/domains/nextplateauent.com/html/" local="3444271200" remote="20624140384" /><file name="P-Dub-TheTransition.jpg" server="s162242.gridserver.com/domains/nextplateauent.com/html/" local="3444271200" remote="20624140384" /><file name="PDub-GoodThang.jpg" server="s162242.gridserver.com/domains/nextplateauent.com/html/" local="3444271200" remote="20624140384" /><file name="PhunkandBeatThrillerz-LoseControlArtwork.JPG" server="s162242.gridserver.com/domains/nextplateauent.com/html/" local="3444271200" remote="20624140384" /><file name="RossCopperman-BleedingLove.jpg" server="s162242.gridserver.com/domains/nextplateauent.com/html/" local="3449192400" remote="20629061584" /><file name="RossCopperman-BleedingLoveCover.jpg" server="s162242.gridserver.com/domains/nextplateauent.com/html/" local="3444271200" remote="20624140384" /><file name="SarahMcLeod-TellYourStoryWalking.jpg" server="s162242.gridserver.com/domains/nextplateauent.com/html/" local="3444271200" remote="20624140384" /><file name="SarahMcLeod-WhiteHorseCover.jpg" server="s162242.gridserver.com/domains/nextplateauent.com/html/" local="3444271200" remote="20624140384" /><file name="Screenshot2013-02-22at10.30.57AM.png" server="s162242.gridserver.com/domains/nextplateauent.com/html/" local="3444357600" remote="20624226784" /><file name="TheSadTruthCoverArt.jpg" server="s162242.gridserver.com/domains/nextplateauent.com/html/" local="3443752800" remote="20623621984" /><file name="TurnUptheRadioCover.jpg" server="s162242.gridserver.com/domains/nextplateauent.com/html/" local="3444271200" remote="20624140384" /><file name="WhatDoesTomorrowBringArtworklowres.jpg" server="s162242.gridserver.com/domains/nextplateauent.com/html/" local="3443752800" remote="20623621984" /><file name="Wideboys&DennisG-Sambuca-Artwork.jpg" server="s162242.gridserver.com/domains/nextplateauent.com/html/" local="3444271200" remote="20624140384" /><file name="WideboysDaddyOCoverArtwork.jpg" server="s162242.gridserver.com/domains/nextplateauent.com/html/" local="3444271200" remote="20624140384" /><file name="Wildstylez-YearofSummer.jpg" server="s162242.gridserver.com/domains/nextplateauent.com/html/" local="3451611600" remote="20631480784" /><file name="beatleschillout1.jpg" server="s162242.gridserver.com/domains/nextplateauent.com/html/" local="3444357600" remote="20624226784" /><file name="championsleaguefinal.jpg" server="s162242.gridserver.com/domains/nextplateauent.com/html/" local="3443148000" remote="20623017184" /><file name="coverlowres.jpg" server="s162242.gridserver.com/domains/nextplateauent.com/html/" local="3443752800" remote="20623621984" /><file name="imcomingoutkatherinellis.jpg" server="s162242.gridserver.com/domains/nextplateauent.com/html/" local="3444357600" remote="20624226784" /><file name="index.jpg" server="s162242.gridserver.com/domains/nextplateauent.com/html/" local="3443493600" remote="20623362784" /><file name="jstatusimready.jpg" server="s162242.gridserver.com/domains/nextplateauent.com/html/" local="3444357600" remote="20624226784" /><file name="jtx_party_insert_web.jpg" server="s162242.gridserver.com/domains/nextplateauent.com/html/" local="3443666400" remote="20623535584" /><file name="katerineayotechnology.jpg" server="s162242.gridserver.com/domains/nextplateauent.com/html/" local="3444357600" remote="20624226784" /><file name="11.jpg" server="s162242.gridserver.com/domains/nextplateauent.com/html/test/" local="3444042900" remote="12042678272" /><file name="13.jpg" server="s162242.gridserver.com/domains/nextplateauent.com/html/test/" local="3444042840" remote="12042678272" /><file name="310152_10150292510055256_5154834_n.jpg" server="s162242.gridserver.com/domains/nextplateauent.com/html/test/" local="3443191200" remote="12042678272" /><file name="33.jpg" server="s162242.gridserver.com/domains/nextplateauent.com/html/test/" local="3444046200" remote="12042678272" /><file name="ADESampler2012lowres.jpg" server="s162242.gridserver.com/domains/nextplateauent.com/html/test/" local="3444406800" remote="12042678272" /><file name="AlexSayz-HateToLovecoverlowres.jpg" server="s162242.gridserver.com/domains/nextplateauent.com/html/test/" local="3443801880" remote="12042678272" /><file name="AlexSayz-ShameOnMeCoverlowres.jpg" server="s162242.gridserver.com/domains/nextplateauent.com/html/test/" local="3443801940" remote="12042678272" /><file name="AlexSayz_UnitedAsOnelowres.jpg" server="s162242.gridserver.com/domains/nextplateauent.com/html/test/" local="3443802060" remote="12042678272" /><file name="AntoineClamaran-Gold.jpg" server="s162242.gridserver.com/domains/nextplateauent.com/html/test/" local="3444324780" remote="12042678272" /><file name="AntoineClamaranLiveYourDreams.jpg" server="s162242.gridserver.com/domains/nextplateauent.com/html/test/" local="3444324780" remote="12042678272" /><file name="AntoineClamaranReachfortheStars.JPG" server="s162242.gridserver.com/domains/nextplateauent.com/html/test/" local="3444325260" remote="12042678272" /><file name="AntoineEclypseArt.JPG" server="s162242.gridserver.com/domains/nextplateauent.com/html/test/" local="3444325320" remote="12042678272" /><file name="Baileyfeat.JodieConor-HigherState.jpg" server="s162242.gridserver.com/domains/nextplateauent.com/html/test/" local="3449236080" remote="12042678272" /><file name="Bailey_HigherState.jpg" server="s162242.gridserver.com/domains/nextplateauent.com/html/test/" local="3443802120" remote="12042678272" /><file name="beatleschillout1.jpg" server="s162242.gridserver.com/domains/nextplateauent.com/html/test/" local="3444414660" remote="12042678272" /><file name="Beckwith-HigherYourLove.JPG" server="s162242.gridserver.com/domains/nextplateauent.com/html/test/" local="3443802300" remote="12042678332" /><file name="Beckwith-NOTIMETOWASTEFinalCover.jpg" server="s162242.gridserver.com/domains/nextplateauent.com/html/test/" local="3443802300" remote="12042678332" /><file name="BeckwithfeatIneabell-Higher(YourLove).jpg" server="s162242.gridserver.com/domains/nextplateauent.com/html/test/" local="3449236200" remote="12042678332" /><file name="BowCoverArtwork.jpg" server="s162242.gridserver.com/domains/nextplateauent.com/html/test/" local="3444327420" remote="12042678332" /><file name="ButterfliesCoverArtwork.jpg" server="s162242.gridserver.com/domains/nextplateauent.com/html/test/" local="3444327720" remote="12042678332" /><file name="championsleaguefinal.jpg" server="s162242.gridserver.com/domains/nextplateauent.com/html/test/" local="3443183100" remote="12042678332" /><file name="ChanelleHayes-IWantIt.jpg" server="s162242.gridserver.com/domains/nextplateauent.com/html/test/" local="3449235960" remote="12042678332" /><file name="ChilloutExperience-BeatlesTributelowres.jpg" server="s162242.gridserver.com/domains/nextplateauent.com/html/test/" local="3444404100" remote="12042678332" /><file name="ConcreteAngelOFFICIALRemixesArtwork.jpg" server="s162242.gridserver.com/domains/nextplateauent.com/html/test/" local="3443800980" remote="12042678332" /><file name="CoverArtDigital-FINALlowres.jpg" server="s162242.gridserver.com/domains/nextplateauent.com/html/test/" local="3443801460" remote="12042678332" /><file name="coverlowres.jpg" server="s162242.gridserver.com/domains/nextplateauent.com/html/test/" local="3443804220" remote="12042678332" /><file name="CraigSmart-123.jpg" server="s162242.gridserver.com/domains/nextplateauent.com/html/test/" local="3449235780" remote="12042678332" /><file name="CraigSmart123CoverArt.jpg" server="s162242.gridserver.com/domains/nextplateauent.com/html/test/" local="3443802540" remote="12042678332" /><file name="DamienS-LongLostSummerLove.jpg" server="s162242.gridserver.com/domains/nextplateauent.com/html/test/" local="3449235840" remote="12042678332" /><file name="DamienS-LongLostSummerLoveArtwork.jpg" server="s162242.gridserver.com/domains/nextplateauent.com/html/test/" local="3443802720" remote="12042678332" /><file name="DavidPuentez-Envy.jpg" server="s162242.gridserver.com/domains/nextplateauent.com/html/test/" local="3449235960" remote="12042678332" /><file name="DavidPuentez-EnvyCoverArt.jpg" server="s162242.gridserver.com/domains/nextplateauent.com/html/test/" local="3443802960" remote="12042678332" /><file name="DavidPuentez-Melodrama.jpg" server="s162242.gridserver.com/domains/nextplateauent.com/html/test/" local="3449235660" remote="12042678332" /><file name="DavidPuentezfeat.AndreaRosario-Melodrama(LoseControlVocal).jpg" server="s162242.gridserver.com/domains/nextplateauent.com/html/test/" local="3449236140" remote="12042678332" /><file name="DavidPuentezfeat.AndreaRosario-Melodrama-LoseControl-Coverart.jpg" server="s162242.gridserver.com/domains/nextplateauent.com/html/test/" local="3443802900" remote="12042678332" /><file name="DavidPuentez_Melodrama_Coverart.jpg" server="s162242.gridserver.com/domains/nextplateauent.com/html/test/" local="3443802780" remote="12042678392" /><file name="DJElla-ShineLikeaSuperstar.jpg" server="s162242.gridserver.com/domains/nextplateauent.com/html/test/" local="3449236020" remote="12042678392" /><file name="DJElla-WelcometotheClub.jpg" server="s162242.gridserver.com/domains/nextplateauent.com/html/test/" local="3449236080" remote="12042678392" /><file name="DJElla_ShineLikeASuperstar_Cover.jpg" server="s162242.gridserver.com/domains/nextplateauent.com/html/test/" local="3443803200" remote="12042678392" /><file name="DJZipDJELLA.jpg" server="s162242.gridserver.com/domains/nextplateauent.com/html/test/" local="3443803200" remote="12042678392" /><file name="Ela-Rose-I-Can-Feel.jpg" server="s162242.gridserver.com/domains/nextplateauent.com/html/test/" local="3443803320" remote="12042678392" /><file name="ElaWardi-IfYouCouldReadMyMind.jpg" server="s162242.gridserver.com/domains/nextplateauent.com/html/test/" local="3449235720" remote="12042678392" /><file name="Ela_Wardi_Stars_on_54Artwork.jpg" server="s162242.gridserver.com/domains/nextplateauent.com/html/test/" local="3443803380" remote="12042678392" /><file name="Freedom_cover.jpg" server="s162242.gridserver.com/domains/nextplateauent.com/html/test/" local="3443801580" remote="12042678392" /><file name="GarethEmeryfeatChristinaNovelli%22ConcreteAngel%22.jpg" server="s162242.gridserver.com/domains/nextplateauent.com/html/test/" local="3443800680" remote="12042678392" /><file name="GarethEmeryfeatChristinaNovelli%22ConcreteAngel%22lowres.jpg" server="s162242.gridserver.com/domains/nextplateauent.com/html/test/" local="3443803740" remote="12042678452" /><file name="GarethEmeryfeatChristinaNovelliConcreteAngellowres.jpg" server="s162242.gridserver.com/domains/nextplateauent.com/html/test/" local="3443803800" remote="12042678452" /><file name="GETFAR-FREE.jpg" server="s162242.gridserver.com/domains/nextplateauent.com/html/test/" local="3443803440" remote="12042678452" /><file name="GetFar-TheRadio.jpg" server="s162242.gridserver.com/domains/nextplateauent.com/html/test/" local="3449236140" remote="12042678452" /><file name="GetFar_TheRadio.jpg" server="s162242.gridserver.com/domains/nextplateauent.com/html/test/" local="3443803440" remote="12042678452" /><file name="GottaLoveForYouCover.jpg" server="s162242.gridserver.com/domains/nextplateauent.com/html/test/" local="3444327060" remote="12042678452" /><file name="HeadShouldersKneezToez.jpg" server="s162242.gridserver.com/domains/nextplateauent.com/html/test/" local="3444325560" remote="12042678452" /><file name="HeartbrokenArtworkCover.jpg" server="s162242.gridserver.com/domains/nextplateauent.com/html/test/" local="3444327720" remote="12042678452" /><file name="HurricaneArtforRelease.jpg" server="s162242.gridserver.com/domains/nextplateauent.com/html/test/" local="3451319040" remote="12042678452" /><file name="IanCareyftSnoopDogg&BobbyAnthony-LastNight(FullCover).jpg" server="s162242.gridserver.com/domains/nextplateauent.com/html/test/" local="3443803560" remote="12042678452" /><file name="IanCareyftSnoopDogg&BobbyAnthony-LastNight(FullCover)lowres.jpg" server="s162242.gridserver.com/domains/nextplateauent.com/html/test/" local="3443803620" remote="12042678452" /><file name="IanCareyftSnoopDoggBobbyAnthony-LastNightlowres.jpg" server="s162242.gridserver.com/domains/nextplateauent.com/html/test/" local="3443804280" remote="12042678452" /><file name="imcomingoutkatherinellis.jpg" server="s162242.gridserver.com/domains/nextplateauent.com/html/test/" local="3444388380" remote="12042678452" /><file name="index.jpg" server="s162242.gridserver.com/domains/nextplateauent.com/html/test/" local="3443516580" remote="12042678452" /><file name="J-Status-AllRise.jpg" server="s162242.gridserver.com/domains/nextplateauent.com/html/test/" local="3444325440" remote="12042678452" /><file name="J-Status-Pieces.jpg" server="s162242.gridserver.com/domains/nextplateauent.com/html/test/" local="3444325500" remote="12042678452" /><file name="Jameerahalleyesonme.jpg" server="s162242.gridserver.com/domains/nextplateauent.com/html/test/" local="3444843300" remote="12042678452" /><file name="JaxBerlin&CoreyPhillips-TheSadTruth.jpg" server="s162242.gridserver.com/domains/nextplateauent.com/html/test/" local="3449235780" remote="12042678452" /><file name="Jersey-Italycopy.jpeg" server="s162242.gridserver.com/domains/nextplateauent.com/html/test/" local="3444404940" remote="12042678452" /><file name="Jersey-Miami-Vol2copy.jpg" server="s162242.gridserver.com/domains/nextplateauent.com/html/test/" local="3444405060" remote="12042678452" /><file name="JerseyMiami_600x600.jpg" server="s162242.gridserver.com/domains/nextplateauent.com/html/test/" local="3444405360" remote="12042678452" /><file name="jstatusimready.jpg" server="s162242.gridserver.com/domains/nextplateauent.com/html/test/" local="3444388620" remote="12042678452" /><file name="JTX-7DayWeekend-iTuneslowres.jpg" server="s162242.gridserver.com/domains/nextplateauent.com/html/test/" local="3443799780" remote="12042678452" /><file name="JTX-LoveInAmerica.jpg" server="s162242.gridserver.com/domains/nextplateauent.com/html/test/" local="3443801040" remote="12042678452" /><file name="JTX-PartyLikeaRockstar.jpg" server="s162242.gridserver.com/domains/nextplateauent.com/html/test/" local="3449235900" remote="12042678452" /><file name="JTXFromDetroitArtwork.jpg" server="s162242.gridserver.com/domains/nextplateauent.com/html/test/" local="3444389040" remote="12042678452" /><file name="JTXLoveinAmericaRemixes.jpg" server="s162242.gridserver.com/domains/nextplateauent.com/html/test/" local="3444388980" remote="12042678452" /><file name="jtx_party_insert_web.jpg" server="s162242.gridserver.com/domains/nextplateauent.com/html/test/" local="3443723160" remote="12042678452" /><file name="Katerine-AyoTechnology(Remixes).jpg" server="s162242.gridserver.com/domains/nextplateauent.com/html/test/" local="3444326100" remote="12042678452" /><file name="katerineayotechnology.jpg" server="s162242.gridserver.com/domains/nextplateauent.com/html/test/" local="3444388500" remote="12042678452" /><file name="KateRyanCover.jpg" server="s162242.gridserver.com/domains/nextplateauent.com/html/test/" local="3444325620" remote="12042678452" /><file name="LiquidNation-BreatheLifeCoverArt.jpg" server="s162242.gridserver.com/domains/nextplateauent.com/html/test/" local="3444326580" remote="12042678452" /><file name="Longo&Wainwright-OneLifeStand.jpg" server="s162242.gridserver.com/domains/nextplateauent.com/html/test/" local="3449235840" remote="12042678452" /><file name="Loveshy-TheBoyisMineCover.jpg" server="s162242.gridserver.com/domains/nextplateauent.com/html/test/" local="3444327120" remote="12042678452" /><file name="Maniacalm-IMissYou.jpg" server="s162242.gridserver.com/domains/nextplateauent.com/html/test/" local="3444327180" remote="12042678452" /><file name="MilanandPhoenixArtwork.jpg" server="s162242.gridserver.com/domains/nextplateauent.com/html/test/" local="3444390720" remote="12042678452" /><file name="MorrisCortiIRockISweatIDanceArtwork.jpg" server="s162242.gridserver.com/domains/nextplateauent.com/html/test/" local="3445015500" remote="12042678512" /><file name="NobodyFallsNewArtworklowres.jpg" server="s162242.gridserver.com/domains/nextplateauent.com/html/test/" local="3443803020" remote="12042678512" /><file name="NPEJoubertSingersTheRemixes2012.jpg" server="s162242.gridserver.com/domains/nextplateauent.com/html/test/" local="3444325440" remote="12042678512" /><file name="NPE_Joubert_Singers.jpg" server="s162242.gridserver.com/domains/nextplateauent.com/html/test/" local="3444325380" remote="12042678512" /><file name="OneLifeStandcover.jpg" server="s162242.gridserver.com/domains/nextplateauent.com/html/test/" local="3444327000" remote="12042678512" /><file name="P-Dub-TheTransition.jpg" server="s162242.gridserver.com/domains/nextplateauent.com/html/test/" local="3444327300" remote="12042678512" /><file name="PDub-GoodThang.jpg" server="s162242.gridserver.com/domains/nextplateauent.com/html/test/" local="3444327300" remote="12042678512" /><file name="PhunkandBeatThrillerz-LoseControlArtwork.JPG" server="s162242.gridserver.com/domains/nextplateauent.com/html/test/" local="3444327240" remote="12042678512" /><file name="RossCopperman-BleedingLove.jpg" server="s162242.gridserver.com/domains/nextplateauent.com/html/test/" local="3449236020" remote="12042678512" /><file name="RossCopperman-BleedingLoveCover.jpg" server="s162242.gridserver.com/domains/nextplateauent.com/html/test/" local="3444327480" remote="12042678512" /><file name="SarahMcLeod-TellYourStoryWalking.jpg" server="s162242.gridserver.com/domains/nextplateauent.com/html/test/" local="3444327540" remote="12042678512" /><file name="SarahMcLeod-WhiteHorseCover.jpg" server="s162242.gridserver.com/domains/nextplateauent.com/html/test/" local="3444327540" remote="12042678512" /><file name="Screenshot2013-02-22at10.30.57AM.png" server="s162242.gridserver.com/domains/nextplateauent.com/html/test/" local="3444388320" remote="12042678512" /><file name="TheSadTruthCoverArt.jpg" server="s162242.gridserver.com/domains/nextplateauent.com/html/test/" local="3443800620" remote="12042678512" /><file name="TurnUptheRadioCover.jpg" server="s162242.gridserver.com/domains/nextplateauent.com/html/test/" local="3444326520" remote="12042678512" /><file name="WhatDoesTomorrowBringArtworklowres.jpg" server="s162242.gridserver.com/domains/nextplateauent.com/html/test/" local="3443801340" remote="12042678512" /><file name="Wideboys&DennisG-Sambuca-Artwork.jpg" server="s162242.gridserver.com/domains/nextplateauent.com/html/test/" local="3444327900" remote="12042678512" /><file name="WideboysDaddyOCoverArtwork.jpg" server="s162242.gridserver.com/domains/nextplateauent.com/html/test/" local="3444327900" remote="12042678512" /><file name="Wildstylez-YearofSummer.jpg" server="s162242.gridserver.com/domains/nextplateauent.com/html/test/" local="3451663860" remote="12042678512" /><file name="JTX-SummerLover.jpg" server="s162242.gridserver.com/domains/nextplateauent.com/html/" local="3453858000" remote="20633727184" /><file name="LOVEEDC2013.jpg" server="s162242.gridserver.com/domains/nextplateauent.com/html/" local="3456912900" remote="20636782084" /><file name="LOVEEDC2013Resized.jpg" server="s162242.gridserver.com/domains/nextplateauent.com/html/" local="3456920580" remote="20636789764" /><file name="Wildstylez-LightsGoOut.jpg" server="s162242.gridserver.com/domains/nextplateauent.com/html/" local="3463738260" remote="20643607444" /><file name="11.jpg" server="ftp.subtextinc.com/NPE/" local="3444012000" remote="12059484452" /><file name="13.jpg" server="ftp.subtextinc.com/NPE/" local="3444012000" remote="12059484452" /><file name="310152_10150292510055256_5154834_n.jpg" server="ftp.subtextinc.com/NPE/" local="3443148000" remote="12059484452" /><file name="33.jpg" server="ftp.subtextinc.com/NPE/" local="3444012000" remote="12059484452" /><file name="ADESampler2012lowres.jpg" server="ftp.subtextinc.com/NPE/" local="3444357600" remote="12059484452" /><file name="AlexSayz-HateToLovecoverlowres.jpg" server="ftp.subtextinc.com/NPE/" local="3443752800" remote="12059484452" /><file name="AlexSayz-ShameOnMeCoverlowres.jpg" server="ftp.subtextinc.com/NPE/" local="3443752800" remote="12059484452" /><file name="AlexSayz_UnitedAsOnelowres.jpg" server="ftp.subtextinc.com/NPE/" local="3443752800" remote="12059484452" /><file name="AntoineClamaran-Gold.jpg" server="ftp.subtextinc.com/NPE/" local="3444271200" remote="12059484452" /><file name="AntoineClamaranLiveYourDreams.jpg" server="ftp.subtextinc.com/NPE/" local="3444271200" remote="12059484452" /><file name="AntoineClamaranReachfortheStars.JPG" server="ftp.subtextinc.com/NPE/" local="3444271200" remote="12059484452" /><file name="AntoineEclypseArt.JPG" server="ftp.subtextinc.com/NPE/" local="3444271200" remote="12059484452" /><file name="Bailey_HigherState.jpg" server="ftp.subtextinc.com/NPE/" local="3443752800" remote="12059484452" /><file name="Baileyfeat.JodieConor-HigherState.jpg" server="ftp.subtextinc.com/NPE/" local="3449192400" remote="12059484452" /><file name="beatleschillout1.jpg" server="ftp.subtextinc.com/NPE/" local="3444357600" remote="12059484452" /><file name="Beckwith-HigherYourLove.JPG" server="ftp.subtextinc.com/NPE/" local="3443752800" remote="12059484452" /><file name="Beckwith-NOTIMETOWASTEFinalCover.jpg" server="ftp.subtextinc.com/NPE/" local="3443752800" remote="12059484452" /><file name="BeckwithfeatIneabell-Higher(YourLove).jpg" server="ftp.subtextinc.com/NPE/" local="3449192400" remote="12059484452" /><file name="BowCoverArtwork.jpg" server="ftp.subtextinc.com/NPE/" local="3444271200" remote="12059484452" /><file name="ButterfliesCoverArtwork.jpg" server="ftp.subtextinc.com/NPE/" local="3444271200" remote="12059484452" /><file name="championsleaguefinal.jpg" server="ftp.subtextinc.com/NPE/" local="3443148000" remote="12059484452" /><file name="ChanelleHayes-IWantIt.jpg" server="ftp.subtextinc.com/NPE/" local="3449192400" remote="12059484452" /><file name="ChilloutExperience-BeatlesTributelowres.jpg" server="ftp.subtextinc.com/NPE/" local="3444357600" remote="12059484452" /><file name="ConcreteAngelOFFICIALRemixesArtwork.jpg" server="ftp.subtextinc.com/NPE/" local="3443752800" remote="12059484452" /><file name="CoverArtDigital-FINALlowres.jpg" server="ftp.subtextinc.com/NPE/" local="3443752800" remote="12059484452" /><file name="coverlowres.jpg" server="ftp.subtextinc.com/NPE/" local="3443752800" remote="12059484512" /><file name="CraigSmart-123.jpg" server="ftp.subtextinc.com/NPE/" local="3449192400" remote="12059484512" /><file name="CraigSmart123CoverArt.jpg" server="ftp.subtextinc.com/NPE/" local="3443752800" remote="12059484512" /><file name="DamienS-LongLostSummerLove.jpg" server="ftp.subtextinc.com/NPE/" local="3449192400" remote="12059484512" /><file name="DamienS-LongLostSummerLoveArtwork.jpg" server="ftp.subtextinc.com/NPE/" local="3443752800" remote="12059484512" /><file name="DavidPuentez-Envy.jpg" server="ftp.subtextinc.com/NPE/" local="3449192400" remote="12059484512" /><file name="DavidPuentez-EnvyCoverArt.jpg" server="ftp.subtextinc.com/NPE/" local="3443752800" remote="12059484512" /><file name="DavidPuentez-Melodrama.jpg" server="ftp.subtextinc.com/NPE/" local="3449192400" remote="12059484512" /><file name="DavidPuentez_Melodrama_Coverart.jpg" server="ftp.subtextinc.com/NPE/" local="3443752800" remote="12059484512" /><file name="DavidPuentezfeat.AndreaRosario-Melodrama(LoseControlVocal).jpg" server="ftp.subtextinc.com/NPE/" local="3449192400" remote="12059484512" /><file name="DavidPuentezfeat.AndreaRosario-Melodrama-LoseControl-Coverart.jpg" server="ftp.subtextinc.com/NPE/" local="3443752800" remote="12059484512" /><file name="default.jpg" server="ftp.subtextinc.com/NPE/" local="3445674012" remote="12059484512" /><file name="DJElla-ShineLikeaSuperstar.jpg" server="ftp.subtextinc.com/NPE/" local="3449192400" remote="12059484512" /><file name="DJElla-WelcometotheClub.jpg" server="ftp.subtextinc.com/NPE/" local="3449192400" remote="12059484512" /><file name="DJElla_ShineLikeASuperstar_Cover.jpg" server="ftp.subtextinc.com/NPE/" local="3443752800" remote="12059484512" /><file name="DJZipDJELLA.jpg" server="ftp.subtextinc.com/NPE/" local="3443752800" remote="12059484512" /><file name="Ela-Rose-I-Can-Feel.jpg" server="ftp.subtextinc.com/NPE/" local="3443752800" remote="12059484512" /><file name="Ela_Wardi_Stars_on_54Artwork.jpg" server="ftp.subtextinc.com/NPE/" local="3443752800" remote="12059484572" /><file name="ElaWardi-IfYouCouldReadMyMind.jpg" server="ftp.subtextinc.com/NPE/" local="3449192400" remote="12059484572" /><file name="Freedom_cover.jpg" server="ftp.subtextinc.com/NPE/" local="3443752800" remote="12059484572" /><file name="GarethEmeryfeatChristinaNovelli%22ConcreteAngel%22.jpg" server="ftp.subtextinc.com/NPE/" local="3443752800" remote="12059484572" /><file name="GarethEmeryfeatChristinaNovelli%22ConcreteAngel%22lowres.jpg" server="ftp.subtextinc.com/NPE/" local="3443752800" remote="12059484572" /><file name="GarethEmeryfeatChristinaNovelliConcreteAngellowres.jpg" server="ftp.subtextinc.com/NPE/" local="3443752800" remote="12059484572" /><file name="GETFAR-FREE.jpg" server="ftp.subtextinc.com/NPE/" local="3443752800" remote="12059484572" /><file name="GetFar-TheRadio.jpg" server="ftp.subtextinc.com/NPE/" local="3449192400" remote="12059484572" /><file name="GetFar_TheRadio.jpg" server="ftp.subtextinc.com/NPE/" local="3443752800" remote="12059484572" /><file name="GottaLoveForYouCover.jpg" server="ftp.subtextinc.com/NPE/" local="3444271200" remote="12059484572" /><file name="HeadShouldersKneezToez.jpg" server="ftp.subtextinc.com/NPE/" local="3444271200" remote="12059484572" /><file name="HeartbrokenArtworkCover.jpg" server="ftp.subtextinc.com/NPE/" local="3444271200" remote="12059484572" /><file name="HurricaneArtforRelease.jpg" server="ftp.subtextinc.com/NPE/" local="3451266000" remote="12059484572" /><file name="IanCareyftSnoopDogg&BobbyAnthony-LastNight(FullCover).jpg" server="ftp.subtextinc.com/NPE/" local="3443752800" remote="12059484572" /><file name="IanCareyftSnoopDogg&BobbyAnthony-LastNight(FullCover)lowres.jpg" server="ftp.subtextinc.com/NPE/" local="3443752800" remote="12059484572" /><file name="IanCareyftSnoopDoggBobbyAnthony-LastNightlowres.jpg" server="ftp.subtextinc.com/NPE/" local="3443752800" remote="12059484572" /><file name="imcomingoutkatherinellis.jpg" server="ftp.subtextinc.com/NPE/" local="3444357600" remote="12059484572" /><file name="index.jpg" server="ftp.subtextinc.com/NPE/" local="3443493600" remote="12059484572" /><file name="J-Status-AllRise.jpg" server="ftp.subtextinc.com/NPE/" local="3444271200" remote="12059484572" /><file name="J-Status-Pieces.jpg" server="ftp.subtextinc.com/NPE/" local="3444271200" remote="12059484572" /><file name="Jameerahalleyesonme.jpg" server="ftp.subtextinc.com/NPE/" local="3444789600" remote="12059484572" /><file name="JaxBerlin&CoreyPhillips-TheSadTruth.jpg" server="ftp.subtextinc.com/NPE/" local="3449192400" remote="12059484572" /><file name="Jersey-Italycopy.jpeg" server="ftp.subtextinc.com/NPE/" local="3444357600" remote="12059484572" /><file name="Jersey-Miami-Vol2copy.jpg" server="ftp.subtextinc.com/NPE/" local="3444357600" remote="12059484572" /><file name="JerseyMiami_600x600.jpg" server="ftp.subtextinc.com/NPE/" local="3444357600" remote="12059484572" /><file name="jstatusimready.jpg" server="ftp.subtextinc.com/NPE/" local="3444357600" remote="12059484572" /><file name="JTX-7DayWeekend-iTuneslowres.jpg" server="ftp.subtextinc.com/NPE/" local="3443752800" remote="12059484572" /><file name="JTX-LoveInAmerica.jpg" server="ftp.subtextinc.com/NPE/" local="3443752800" remote="12059484632" /><file name="JTX-PartyLikeaRockstar.jpg" server="ftp.subtextinc.com/NPE/" local="3449192400" remote="12059484632" /><file name="jtx_party_insert_web.jpg" server="ftp.subtextinc.com/NPE/" local="3443666400" remote="12059484632" /><file name="JTXFromDetroitArtwork.jpg" server="ftp.subtextinc.com/NPE/" local="3444357600" remote="12059484632" /><file name="JTXLoveinAmericaRemixes.jpg" server="ftp.subtextinc.com/NPE/" local="3444357600" remote="12059484632" /><file name="Katerine-AyoTechnology(Remixes).jpg" server="ftp.subtextinc.com/NPE/" local="3444271200" remote="12059484632" /><file name="katerineayotechnology.jpg" server="ftp.subtextinc.com/NPE/" local="3444357600" remote="12059484632" /><file name="KateRyanCover.jpg" server="ftp.subtextinc.com/NPE/" local="3444271200" remote="12059484632" /><file name="LiquidNation-BreatheLifeCoverArt.jpg" server="ftp.subtextinc.com/NPE/" local="3444271200" remote="12059484632" /><file name="Longo&Wainwright-OneLifeStand.jpg" server="ftp.subtextinc.com/NPE/" local="3449192400" remote="12059484632" /><file name="Loveshy-TheBoyisMineCover.jpg" server="ftp.subtextinc.com/NPE/" local="3444271200" remote="12059484632" /><file name="Maniacalm-IMissYou.jpg" server="ftp.subtextinc.com/NPE/" local="3444271200" remote="12059484632" /><file name="MilanandPhoenixArtwork.jpg" server="ftp.subtextinc.com/NPE/" local="3444357600" remote="12059484632" /><file name="MorrisCortiIRockISweatIDanceArtwork.jpg" server="ftp.subtextinc.com/NPE/" local="3444962400" remote="12059484632" /><file name="NobodyFallsNewArtworklowres.jpg" server="ftp.subtextinc.com/NPE/" local="3443752800" remote="12059484632" /><file name="np2814.jpg" server="ftp.subtextinc.com/NPE/" local="3442975200" remote="12059484632" /><file name="np2816.jpg" server="ftp.subtextinc.com/NPE/" local="3442975200" remote="12059484632" /><file name="np2820.jpg" server="ftp.subtextinc.com/NPE/" local="3442975200" remote="12059484632" /><file name="NPE_Joubert_Singers.jpg" server="ftp.subtextinc.com/NPE/" local="3444271200" remote="12059484632" /><file name="NPEJoubertSingersTheRemixes2012.jpg" server="ftp.subtextinc.com/NPE/" local="3444271200" remote="12059484632" /><file name="OneLifeStandcover.jpg" server="ftp.subtextinc.com/NPE/" local="3444271200" remote="12059484632" /><file name="P-Dub-TheTransition.jpg" server="ftp.subtextinc.com/NPE/" local="3444271200" remote="12059484632" /><file name="PDub-GoodThang.jpg" server="ftp.subtextinc.com/NPE/" local="3444271200" remote="12059484632" /><file name="PhunkandBeatThrillerz-LoseControlArtwork.JPG" server="ftp.subtextinc.com/NPE/" local="3444271200" remote="12059484632" /><file name="rca.jpg" server="ftp.subtextinc.com/NPE/" local="3442975200" remote="12059484632" /><file name="RossCopperman-BleedingLove.jpg" server="ftp.subtextinc.com/NPE/" local="3449192400" remote="12059484632" /><file name="RossCopperman-BleedingLoveCover.jpg" server="ftp.subtextinc.com/NPE/" local="3444271200" remote="12059484632" /><file name="SarahMcLeod-TellYourStoryWalking.jpg" server="ftp.subtextinc.com/NPE/" local="3444271200" remote="12059484632" /><file name="SarahMcLeod-WhiteHorseCover.jpg" server="ftp.subtextinc.com/NPE/" local="3444271200" remote="12059484632" /><file name="Screenshot2013-02-22at10.30.57AM.png" server="ftp.subtextinc.com/NPE/" local="3444357600" remote="12059484632" /><file name="tce2.jpg" server="ftp.subtextinc.com/NPE/" local="3442975200" remote="12059484632" /><file name="TheSadTruthCoverArt.jpg" server="ftp.subtextinc.com/NPE/" local="3443752800" remote="12059484692" /><file name="TurnUptheRadioCover.jpg" server="ftp.subtextinc.com/NPE/" local="3444271200" remote="12059484692" /><file name="WhatDoesTomorrowBringArtworklowres.jpg" server="ftp.subtextinc.com/NPE/" local="3443752800" remote="12059484692" /><file name="Wideboys&DennisG-Sambuca-Artwork.jpg" server="ftp.subtextinc.com/NPE/" local="3444271200" remote="12059484692" /><file name="WideboysDaddyOCoverArtwork.jpg" server="ftp.subtextinc.com/NPE/" local="3444271200" remote="12059484692" /><file name="Wildstylez-YearofSummer.jpg" server="ftp.subtextinc.com/NPE/" local="3451611600" remote="12059484692" /><file name="JTX-SummerLover.jpg" server="ftp.subtextinc.com/NPE/" local="3453858000" remote="12059484692" /><file name="LOVEEDC2013.jpg" server="ftp.subtextinc.com/NPE/" local="3456912900" remote="12059484692" /><file name="LOVEEDC2013Resized.jpg" server="ftp.subtextinc.com/NPE/" local="3456920580" remote="12059484692" /><file name="Wildstylez-LightsGoOut.jpg" server="ftp.subtextinc.com/NPE/" local="3463738260" remote="12059484692" /></dwsync>